errant/__init__.py
errant/alignment.py
errant/annotator.py
errant/edit.py
errant/commands/__init__.py
errant/commands/compare_m2.py
errant/commands/m2_to_m2.py
errant/commands/parallel_to_m2.py
errant/en/__init__.py
errant/en/classifier.py
errant/en/lancaster.py
errant/en/merger.py
errant/en/resources/README.md
errant/en/resources/en-ptb_map
errant/en/resources/en_GB-large.txt
errant/ru/__init__.py
errant/ru/classifier.py
errant/ru/merger.py
ru_errant-2.3.0.dist-info/LICENSE.md
ru_errant-2.3.0.dist-info/METADATA
ru_errant-2.3.0.dist-info/WHEEL
ru_errant-2.3.0.dist-info/entry_points.txt
ru_errant-2.3.0.dist-info/top_level.txt
ru_errant-2.3.0.dist-info/RECORD
